<Spawn id="spawn">
	<Head>
		<meta name="title" value="New File"/>
		<meta name="width" value="840" min="580"/>
		<meta name="height" value="560" min="300"/>
		<meta name="top" value="170"/>
		<meta name="left" value="240"/>
		<meta name="minimize"/>
		<meta name="maximize"/>
		<meta name="resize"/>
		<meta name="allowTabs"/>
		<meta name="style" value="../css/main.less"/>
		<meta name="toolbar-style" value="../css/toolbar.less"/>
		<meta name="content" value="content.htm"/>

		@import "toolbar.xml"
	</Head>
</Spawn>